Metadata-Version: 2.1
Name: p5.new-service-port-generator
Version: 0.0.2
Summary: UNKNOWN
Home-page: https://github.com/p5-vbnekit/p5-python-new_service_port_generator
Author: p5-vbnekit
Author-email: vbnekit@gmail.com
License: GPL-3.0
Platform: UNKNOWN
